PyGHub/__init__.py
PyGHub/pyghub.py
PyGHub/user.py
PyGHub-0.0.4.dist-info/LICENSE
PyGHub-0.0.4.dist-info/METADATA
PyGHub-0.0.4.dist-info/WHEEL
PyGHub-0.0.4.dist-info/top_level.txt
PyGHub-0.0.4.dist-info/RECORD
