Metadata-Version: 2.1
Name: PyGHub
Version: 0.0.4
Summary: A github module for Python 
Home-page: https://github.com/FRostri/PyGHub
Author: FRostri
Author-email: frostri.sho755@gmail.com
License: UNKNOWN
Platform: UNKNOWN
Classifier: Programming Language :: Python :: 3
Classifier: Development Status :: 2 - Pre-Alpha
Classifier: Intended Audience :: Developers
Classifier: Topic :: Software Development :: Version Control
Classifier: Topic :: Software Development :: Version Control :: Git
Classifier: License :: OSI Approved :: MIT License
Classifier: Operating System :: OS Independent
Requires-Python: >=3.6
Requires-Dist: requests
